<?xml version="1.0" encoding="utf-8"?>
<!DOCTYPE EwdTree SYSTEM "../../../dtd/ewdtree.dtd">
<EwdTree ver="2.3.1.16" pubno="EM25TBE" xml:lang="en">
  <note ewd="WIRE033" code="Q2" type="conn">
    <name>Rear Door Lock Actuator Assembly LH</name>
  </note>
  <note ewd="WIRE033" code="Q3" type="conn">
    <name>Rear Power Window Regulator Motor Assembly LH</name>
  </note>
  <note ewd="WIRE033" code="Q1" type="conn">
    <name>Rear Power Window Regulator Switch Assembly LH</name>
  </note>
  <note ewd="WIRE033" code="QU1" type="w2w">
    <name>No. 2 Rear Door Wire and No. 3 Floor Wire</name>
  </note>
</EwdTree>